Metadata-Version: 1.0
Name: mymathFoo1
Version: 0.5
Summary: Silly little math turd to add/subtract.
Home-page: UNKNOWN
Author: shubham katariya
Author-email: shubham.katariya@newput.com
License: UNKNOWN
Platform: UNKNOWN
